pydantify/__init__.py
pydantify/__main__.py
pydantify/exceptions.py
pydantify/main.py
pydantify/models/__init__.py
pydantify/models/base.py
pydantify/models/models.py
pydantify/models/nodefactory.py
pydantify/models/typeresolver.py
pydantify/plugins/__init__.py
pydantify/plugins/pydantic_plugin.py
pydantify/utility/__init__.py
pydantify/utility/function_tools.py
pydantify/utility/model_generator.py
pydantify/utility/patterns.py
pydantify/utility/restconf.py
pydantify/utility/yang_sources_tracker.py
pydantify-0.9.0.dist-info/WHEEL
pydantify-0.9.0.dist-info/entry_points.txt
pydantify-0.9.0.dist-info/METADATA
pydantify-0.9.0.dist-info/RECORD
