Metadata-Version: 2.3
Name: pydantify
Version: 0.9.0
Summary: Makes network automation pydantic.
Author: Dominic Walther, Dejan Jovicic, Urs Baumann
Author-email: Dominic Walther <dominic.walther@ost.ch>, Dejan Jovicic <dejan.jovicic@ost.ch>, Urs Baumann <github@m.ubaumann.ch>
License: MIT
Classifier: Development Status :: 4 - Beta
Classifier: Intended Audience :: Developers
Classifier: Operating System :: OS Independent
Requires-Dist: pydantic==2.11.7
Requires-Dist: pyang==2.6.1
Requires-Dist: psutil>=6.0.0
Requires-Dist: datamodel-code-generator==0.32.0
Requires-Dist: requests>=2.32.3
Requires-Dist: setuptools>=74.0.0
Requires-Python: >=3.10
Project-URL: Changelog, https://github.com/pydantify/pydantify/releases
Project-URL: Documentation, https://pydantify.github.io/pydantify/
Project-URL: Homepage, https://pydantify.github.io/pydantify/
Project-URL: Issues, https://github.com/pydantify/pydantify/issues
Project-URL: Repository, https://github.com/pydantify/pydantify
